binhosupernova/__init__.py
binhosupernova/supernova.py
binhosupernova/commands/__init__.py
binhosupernova/commands/common_definitions.py
binhosupernova/commands/gpio/__init__.py
binhosupernova/commands/gpio/definitions.py
binhosupernova/commands/gpio/serializers.py
binhosupernova/commands/gpio/validators.py
binhosupernova/commands/helpers/__init__.py
binhosupernova/commands/helpers/validator.py
binhosupernova/commands/i2c/__init__.py
binhosupernova/commands/i2c/definitions.py
binhosupernova/commands/i2c/serializers.py
binhosupernova/commands/i2c/validators.py
binhosupernova/commands/i3c/__init__.py
binhosupernova/commands/i3c/definitions.py
binhosupernova/commands/i3c/serializers.py
binhosupernova/commands/i3c/validators.py
binhosupernova/commands/spi/__init__.py
binhosupernova/commands/spi/definitions.py
binhosupernova/commands/spi/serializers.py
binhosupernova/commands/spi/validators.py
binhosupernova/commands/system/__init__.py
binhosupernova/commands/system/definitions.py
binhosupernova/commands/system/serializers.py
binhosupernova/commands/system/validators.py
binhosupernova/commands/uart/__init__.py
binhosupernova/commands/uart/definitions.py
binhosupernova/commands/uart/serializers.py
binhosupernova/commands/uart/validators.py
binhosupernova/usb/__init__.py
binhosupernova/usb/usb_hid_manager.py
binhosupernova/usb/usb_transfer_protocol.py
binhosupernova/utils/__init__.py
binhosupernova/utils/system_message.py
binhosupernova-4.2.0.dist-info/LICENSE
binhosupernova-4.2.0.dist-info/METADATA
binhosupernova-4.2.0.dist-info/WHEEL
binhosupernova-4.2.0.dist-info/top_level.txt
binhosupernova-4.2.0.dist-info/RECORD
