Metadata-Version: 2.1
Name: binhosupernova
Version: 4.2.0
Summary: Python package for Binho Supernova USB host adapter
Home-page: https://binho.io
Author: Binho LLC
Author-email: support@binho.io
License: BSD
Platform: any
Classifier: Programming Language :: Python
Classifier: Development Status :: 1 - Planning
Classifier: Natural Language :: English
Classifier: Environment :: Console
Classifier: Environment :: Plugins
Classifier: Intended Audience :: Developers
Classifier: Intended Audience :: Science/Research
Classifier: License :: OSI Approved :: BSD License
Classifier: Operating System :: OS Independent
Classifier: Topic :: Scientific/Engineering
Requires-Python: >=3.8
License-File: LICENSE
Requires-Dist: pyserial
Requires-Dist: hidapi
Requires-Dist: psutil
